coincurve/context.pyi
coincurve/keys.pyi
coincurve/py.typed
coincurve/utils.pyi
coincurve_stubs-9.0.0.dist-info/METADATA
coincurve_stubs-9.0.0.dist-info/RECORD
coincurve_stubs-9.0.0.dist-info/WHEEL
coincurve_stubs-9.0.0.dist-info/top_level.txt
