Metadata-Version: 2.1
Name: coincurve-stubs
Version: 9.0.0
Summary: Stubs, i.e., type information, for Coincurve
Home-page: https://github.com/planetarium/coincurve-stubs
Author: Hong Minhee
Author-email: hong.minhee@gmail.com
License: MIT
Platform: UNKNOWN
Classifier: Development Status :: 3 - Alpha
Classifier: Intended Audience :: Developers
Classifier: License :: OSI Approved :: MIT License
Classifier: Operating System :: OS Independent
Classifier: Programming Language :: Python :: 3.5
Classifier: Programming Language :: Python :: 3.6
Classifier: Programming Language :: Python :: 3.7
Classifier: Programming Language :: Python :: 3.8
Classifier: Topic :: Software Development
